list2dpro/__init__.py
list2dpro/data_operations.py
list2dpro/math_operations.py
list2dpro-0.2.1.dist-info/licenses/LICENSE
tests/__init__.py
tests/test_data_operations.py
tests/test_math_operations.py
list2dpro-0.2.1.dist-info/METADATA
list2dpro-0.2.1.dist-info/WHEEL
list2dpro-0.2.1.dist-info/top_level.txt
list2dpro-0.2.1.dist-info/RECORD
