Metadata-Version: 2.4
Name: list2dpro
Version: 0.2.1
Summary: A comprehensive 2D list manipulation library for Python with four specialized classes: List2DEdit (basic editing), List2DGame (game development), List2DMath (mathematical operations), and List2DData (data processing).
Home-page: 
Author: FriskYan
Author-email: 476227421@qq.com
Classifier: Development Status :: 3 - Alpha
Classifier: Intended Audience :: Developers
Classifier: Topic :: Software Development :: Libraries
Classifier: License :: OSI Approved :: MIT License
Classifier: Programming Language :: Python :: 3
Classifier: Programming Language :: Python :: 3.6
Classifier: Programming Language :: Python :: 3.7
Classifier: Programming Language :: Python :: 3.8
Classifier: Programming Language :: Python :: 3.9
Classifier: Programming Language :: Python :: 3.10
Requires-Python: >=3.6
License-File: LICENSE
Dynamic: author
Dynamic: author-email
Dynamic: classifier
Dynamic: description
Dynamic: description-content-type
Dynamic: license-file
Dynamic: requires-python
Dynamic: summary
